prashantadder/__init__.py
prashantadder/adder.py
prashantadder-0.0.1.dist-info/licenses/LICENSE
prashantadder-0.0.1.dist-info/METADATA
prashantadder-0.0.1.dist-info/WHEEL
prashantadder-0.0.1.dist-info/top_level.txt
prashantadder-0.0.1.dist-info/RECORD
