Metadata-Version: 2.4
Name: prashantadder
Version: 0.0.1
Summary: This package adds two numbers
Author-email: Prashant Chapagain <prashantchapagain@gmail.com>
License-Expression: MIT
Project-URL: Homepage, https://github.com/pypa/sampleproject
Project-URL: Issues, https://github.com/pypa/sampleproject/issues
Classifier: Programming Language :: Python :: 3
Classifier: Operating System :: OS Independent
Requires-Python: >=3.9
License-File: LICENSE
Dynamic: license-file
